[{"n":"Ross Seymore","f":"Deutsche Bank ","st":5,"r":"Buy","pt":1850,"opt":1300,"d":"2026-05-01"},{"n":"Kevin Cassidy","f":"Rosenblatt Securities","st":5,"r":"Hold","pt":1575,"opt":1000,"d":"2026-05-01"},{"n":"Quinn Bolton","f":"Needham","st":5,"r":"Buy","pt":1750,"opt":null,"d":"2026-05-01"},{"n":"Tore Svanberg","f":"Stifel Nicolaus","st":5,"r":"Buy","pt":1800,"opt":1500,"d":"2026-05-01"},{"n":"William Stein","f":"Truist Financial","st":5,"r":"Buy","pt":1805,"opt":1396,"d":"2026-05-01"},{"n":"Melissa Fairbanks","f":"Raymond James","st":4.9,"r":"Buy","pt":1800,"opt":1350,"d":"2026-05-01"},{"n":"Joshua Buchalter","f":"TD Cowen","st":5,"r":"Buy","pt":1850,"opt":1550,"d":"2026-04-30"},{"n":"Chris Caso","f":"Wolfe Research","st":5,"r":"Buy","pt":1200,"opt":null,"d":"2025-10-14"},{"n":"Gary Mobley","f":"Loop Capital Markets","st":4.8,"r":"Buy","pt":800,"opt":null,"d":"2025-08-01"},{"n":"Kevin Garrigan","f":"Jefferies","st":4.3,"r":"Hold","pt":800,"opt":644,"d":"2025-08-01"}]