[{"n":"Matthew O'Brien","f":"Piper Sandler","st":0.1,"r":"Buy","pt":210,"opt":null,"d":"2026-06-15"},{"n":"Marie Thibault","f":"BTIG","st":0,"r":"Buy","pt":235,"opt":null,"d":"2026-06-15"},{"n":"Richard Newitter","f":"Truist Financial","st":4.3,"r":"Buy","pt":219,"opt":250,"d":"2026-06-12"},{"n":"Jayson Bedford","f":"Raymond James","st":4.7,"r":"Buy","pt":216,"opt":263,"d":"2026-06-08"},{"n":"Larry Biegelsen","f":"Wells Fargo","st":3.4,"r":"Buy","pt":255,"opt":null,"d":"2026-06-08"},{"n":"Matt Miksic","f":"Barclays","st":3.3,"r":"Sell","pt":198,"opt":null,"d":"2026-05-28"},{"n":"David Roman","f":"Goldman Sachs","st":3.3,"r":"Buy","pt":205,"opt":237,"d":"2026-05-27"},{"n":"Shagun Singh Chadha","f":"RBC Capital","st":0.7,"r":"Buy","pt":280,"opt":null,"d":"2026-05-27"},{"n":"Bruce Jackson","f":"Benchmark Co.","st":0.1,"r":"Buy","pt":250,"opt":null,"d":"2026-05-12"},{"n":"Jeff Johnson","f":"Robert W. Baird","st":4.5,"r":"Buy","pt":248,"opt":360,"d":"2026-05-07"},{"n":"Robbie Marcus","f":"J.P. Morgan","st":4.2,"r":"Buy","pt":275,"opt":340,"d":"2026-05-07"},{"n":"Suraj Kalia","f":"Oppenheimer","st":4.2,"r":"Buy","pt":210,"opt":300,"d":"2026-05-07"},{"n":"William Plovanic","f":"Canaccord Genuity","st":2,"r":"Buy","pt":249,"opt":435,"d":"2026-05-07"},{"n":"Lee Hambright","f":"Bernstein","st":0.6,"r":"Buy","pt":200,"opt":330,"d":"2026-05-07"},{"n":"Andrew Ranieri","f":"TD Cowen","st":0.6,"r":"Hold","pt":294,"opt":null,"d":"2026-05-06"},{"n":"Issie Kirby","f":"Rothschild & Co Redburn","st":1.1,"r":"Hold","pt":220,"opt":380,"d":"2026-04-24"},{"n":"Patrick Wood","f":"Morgan Stanley","st":0.4,"r":"Buy","pt":370,"opt":null,"d":"2026-02-20"},{"n":"Matthew Taylor","f":"Jefferies","st":4.4,"r":"Buy","pt":400,"opt":null,"d":"2026-02-19"},{"n":"Danielle Antalffy","f":"UBS","st":3.4,"r":"Buy","pt":400,"opt":null,"d":"2026-02-19"},{"n":"Mike Kratky","f":"Leerink Partners","st":4.3,"r":"Buy","pt":355,"opt":339,"d":"2025-10-14"}]